<?xml version="1.0" encoding="UTF-8" standalone="yes"?>
<unit xmlns="http://www.srcML.org/srcML/src" xmlns:cpp="http://www.srcML.org/srcML/cpp" revision="1.0.0" language="C" filename="/home/user/cppstats/test/freeBSD_res/_cppstats_featurelocations/freebsd-src/contrib/llvm-project/lldb/include/lldb/API/SBCommandInterpreterRunOptions.h">







<cpp:if>#<cpp:directive>if</cpp:directive> <expr><operator>!</operator><call><name>defined</name><argument_list>(<argument><expr><name>LLDB_API_SBCOMMANDINTERPRETERRUNOPTIONS_H</name></expr></argument>)</argument_list></call></expr></cpp:if>
<cpp:define>#<cpp:directive>define</cpp:directive> <cpp:macro><name>LLDB_API_SBCOMMANDINTERPRETERRUNOPTIONS_H</name></cpp:macro></cpp:define>

<cpp:include>#<cpp:directive>include</cpp:directive> <cpp:file>&lt;memory&gt;</cpp:file></cpp:include>

<cpp:include>#<cpp:directive>include</cpp:directive> <cpp:file>"lldb/API/SBDefines.h"</cpp:file></cpp:include>

<decl_stmt><decl><type><name>namespace</name></type> <name>lldb_private</name> <block>{<block_content>
<decl_stmt><decl><type><name>class</name></type> <name>CommandInterpreterRunOptions</name></decl>;</decl_stmt>
<decl_stmt><decl><type><name>class</name></type> <name>CommandInterpreterRunResult</name></decl>;</decl_stmt>
</block_content>}</block></decl></decl_stmt>

<decl_stmt><decl><type><name>namespace</name></type> <name>lldb</name> <block>{<block_content>

<decl_stmt><decl><type><name>class</name> <name>LLDB_API</name></type> <name>SBCommandInterpreterRunOptions</name> <block>{<block_content>
<decl_stmt><decl><type><name>friend</name> <name>class</name></type> <name>SBDebugger</name></decl>;</decl_stmt>
<decl_stmt><decl><type><name>friend</name> <name>class</name></type> <name>SBCommandInterpreter</name></decl>;</decl_stmt>

<label><name>public</name>:</label>
<expr_stmt><expr><call><name>SBCommandInterpreterRunOptions</name><argument_list>()</argument_list></call></expr>;</expr_stmt>
<expr_stmt><expr><call><name>SBCommandInterpreterRunOptions</name><argument_list>(<argument><expr><specifier>const</specifier> <name>SBCommandInterpreterRunOptions</name> <operator>&amp;</operator><name>rhs</name></expr></argument>)</argument_list></call></expr>;</expr_stmt>
<expr_stmt><expr><operator>~</operator><call><name>SBCommandInterpreterRunOptions</name><argument_list>()</argument_list></call></expr>;</expr_stmt>

<decl_stmt><decl><type><name>SBCommandInterpreterRunOptions</name> <modifier>&amp;</modifier></type>
<name>operator</name><init>=<expr><operator>(</operator><specifier>const</specifier> <name>SBCommandInterpreterRunOptions</name> <operator>&amp;</operator><name>rhs</name><operator>)</operator></expr></init></decl>;</decl_stmt>

<expr_stmt><expr><name>bool</name> <macro><name>GetStopOnContinue</name><argument_list>()</argument_list></macro> <specifier>const</specifier></expr>;</expr_stmt>

<function_decl><type><name>void</name></type> <name>SetStopOnContinue</name><parameter_list>(<parameter><decl><type><name>bool</name></type></decl></parameter>)</parameter_list>;</function_decl>

<expr_stmt><expr><name>bool</name> <macro><name>GetStopOnError</name><argument_list>()</argument_list></macro> <specifier>const</specifier></expr>;</expr_stmt>

<function_decl><type><name>void</name></type> <name>SetStopOnError</name><parameter_list>(<parameter><decl><type><name>bool</name></type></decl></parameter>)</parameter_list>;</function_decl>

<expr_stmt><expr><name>bool</name> <macro><name>GetStopOnCrash</name><argument_list>()</argument_list></macro> <specifier>const</specifier></expr>;</expr_stmt>

<function_decl><type><name>void</name></type> <name>SetStopOnCrash</name><parameter_list>(<parameter><decl><type><name>bool</name></type></decl></parameter>)</parameter_list>;</function_decl>

<expr_stmt><expr><name>bool</name> <macro><name>GetEchoCommands</name><argument_list>()</argument_list></macro> <specifier>const</specifier></expr>;</expr_stmt>

<function_decl><type><name>void</name></type> <name>SetEchoCommands</name><parameter_list>(<parameter><decl><type><name>bool</name></type></decl></parameter>)</parameter_list>;</function_decl>

<expr_stmt><expr><name>bool</name> <macro><name>GetEchoCommentCommands</name><argument_list>()</argument_list></macro> <specifier>const</specifier></expr>;</expr_stmt>

<function_decl><type><name>void</name></type> <name>SetEchoCommentCommands</name><parameter_list>(<parameter><decl><type><name>bool</name></type> <name>echo</name></decl></parameter>)</parameter_list>;</function_decl>

<expr_stmt><expr><name>bool</name> <macro><name>GetPrintResults</name><argument_list>()</argument_list></macro> <specifier>const</specifier></expr>;</expr_stmt>

<function_decl><type><name>void</name></type> <name>SetPrintResults</name><parameter_list>(<parameter><decl><type><name>bool</name></type></decl></parameter>)</parameter_list>;</function_decl>

<expr_stmt><expr><name>bool</name> <macro><name>GetPrintErrors</name><argument_list>()</argument_list></macro> <specifier>const</specifier></expr>;</expr_stmt>

<function_decl><type><name>void</name></type> <name>SetPrintErrors</name><parameter_list>(<parameter><decl><type><name>bool</name></type></decl></parameter>)</parameter_list>;</function_decl>

<expr_stmt><expr><name>bool</name> <macro><name>GetAddToHistory</name><argument_list>()</argument_list></macro> <specifier>const</specifier></expr>;</expr_stmt>

<function_decl><type><name>void</name></type> <name>SetAddToHistory</name><parameter_list>(<parameter><decl><type><name>bool</name></type></decl></parameter>)</parameter_list>;</function_decl>

<expr_stmt><expr><name>bool</name> <macro><name>GetAutoHandleEvents</name><argument_list>()</argument_list></macro> <specifier>const</specifier></expr>;</expr_stmt>

<function_decl><type><name>void</name></type> <name>SetAutoHandleEvents</name><parameter_list>(<parameter><decl><type><name>bool</name></type></decl></parameter>)</parameter_list>;</function_decl>

<expr_stmt><expr><name>bool</name> <macro><name>GetSpawnThread</name><argument_list>()</argument_list></macro> <specifier>const</specifier></expr>;</expr_stmt>

<function_decl><type><name>void</name></type> <name>SetSpawnThread</name><parameter_list>(<parameter><decl><type><name>bool</name></type></decl></parameter>)</parameter_list>;</function_decl>

<label><name>private</name>:</label>
<expr_stmt><expr><name>lldb_private</name><operator>::</operator><name>CommandInterpreterRunOptions</name> <operator>*</operator><macro><name>get</name><argument_list>()</argument_list></macro> <specifier>const</specifier></expr>;</expr_stmt>

<expr_stmt><expr><name>lldb_private</name><operator>::</operator><name>CommandInterpreterRunOptions</name> <operator>&amp;</operator><macro><name>ref</name><argument_list>()</argument_list></macro> <specifier>const</specifier></expr>;</expr_stmt>


<expr_stmt><expr><name>mutable</name> <name>std</name><operator>::</operator><name><name>unique_ptr</name><argument_list type="generic">&lt;<argument><expr><name>lldb_private</name><operator>::</operator><name>CommandInterpreterRunOptions</name></expr></argument>&gt;</argument_list></name>
<name>m_opaque_up</name></expr>;</expr_stmt>
</block_content>}</block></decl></decl_stmt><empty_stmt>;</empty_stmt>

<decl_stmt><decl><type><name>class</name> <name>LLDB_API</name></type> <name>SBCommandInterpreterRunResult</name> <block>{<block_content>
<decl_stmt><decl><type><name>friend</name> <name>class</name></type> <name>SBDebugger</name></decl>;</decl_stmt>
<decl_stmt><decl><type><name>friend</name> <name>class</name></type> <name>SBCommandInterpreter</name></decl>;</decl_stmt>

<label><name>public</name>:</label>
<expr_stmt><expr><call><name>SBCommandInterpreterRunResult</name><argument_list>()</argument_list></call></expr>;</expr_stmt>
<expr_stmt><expr><call><name>SBCommandInterpreterRunResult</name><argument_list>(<argument><expr><specifier>const</specifier> <name>SBCommandInterpreterRunResult</name> <operator>&amp;</operator><name>rhs</name></expr></argument>)</argument_list></call></expr>;</expr_stmt>
<expr_stmt><expr><operator>~</operator><call><name>SBCommandInterpreterRunResult</name><argument_list>()</argument_list></call></expr>;</expr_stmt>

<decl_stmt><decl><type><name>SBCommandInterpreterRunResult</name> <modifier>&amp;</modifier></type>
<name>operator</name><init>=<expr><operator>(</operator><specifier>const</specifier> <name>SBCommandInterpreterRunResult</name> <operator>&amp;</operator><name>rhs</name><operator>)</operator></expr></init></decl>;</decl_stmt>

<expr_stmt><expr><name>int</name> <macro><name>GetNumberOfErrors</name><argument_list>()</argument_list></macro> <specifier>const</specifier></expr>;</expr_stmt>
<expr_stmt><expr><name>lldb</name><operator>::</operator><name>CommandInterpreterResult</name> <macro><name>GetResult</name><argument_list>()</argument_list></macro> <specifier>const</specifier></expr>;</expr_stmt>

<label><name>private</name>:</label>
<expr_stmt><expr><call><name>SBCommandInterpreterRunResult</name><argument_list>(
<argument><expr><specifier>const</specifier> <name>lldb_private</name><operator>::</operator><name>CommandInterpreterRunResult</name> <operator>&amp;</operator><name>rhs</name></expr></argument>)</argument_list></call></expr>;</expr_stmt>


<expr_stmt><expr><name>std</name><operator>::</operator><name><name>unique_ptr</name><argument_list type="generic">&lt;<argument><expr><name>lldb_private</name><operator>::</operator><name>CommandInterpreterRunResult</name></expr></argument>&gt;</argument_list></name> <name>m_opaque_up</name></expr>;</expr_stmt>
</block_content>}</block></decl></decl_stmt><empty_stmt>;</empty_stmt>

</block_content>}</block></decl></decl_stmt>

<cpp:endif>#<cpp:directive>endif</cpp:directive></cpp:endif>
</unit>
