<?xml version="1.0" encoding="UTF-8" standalone="yes"?>
<unit xmlns="http://www.srcML.org/srcML/src" xmlns:cpp="http://www.srcML.org/srcML/cpp" revision="1.0.0" language="C" filename="/home/user/cppstats/test/freeBSD_res/_cppstats_featurelocations/freebsd-src/cddl/contrib/opensolaris/head/libintl.h">



























<cpp:if>#<cpp:directive>if</cpp:directive> <expr><operator>!</operator><call><name>defined</name><argument_list>(<argument><expr><name>_LIBINTL_H</name></expr></argument>)</argument_list></call></expr></cpp:if>
<cpp:define>#<cpp:directive>define</cpp:directive> <cpp:macro><name>_LIBINTL_H</name></cpp:macro></cpp:define>

<cpp:include>#<cpp:directive>include</cpp:directive> <cpp:file>&lt;sys/isa_defs.h&gt;</cpp:file></cpp:include>

<cpp:if>#<cpp:directive>if</cpp:directive> <expr><call><name>defined</name><argument_list>(<argument><expr><name>__cplusplus</name></expr></argument>)</argument_list></call></expr></cpp:if>
<extern>extern <literal type="string">"C"</literal> <block>{<block_content>
<cpp:endif>#<cpp:directive>endif</cpp:directive></cpp:endif>














<cpp:if>#<cpp:directive>if</cpp:directive> <expr><operator>!</operator><call><name>defined</name><argument_list>(<argument><expr><name>__cplusplus</name></expr></argument>)</argument_list></call> <operator>||</operator> <operator>(</operator><name>__cplusplus</name> <operator>&lt;</operator> <literal type="number">199711L</literal> <operator>&amp;&amp;</operator> <operator>!</operator><call><name>defined</name><argument_list>(<argument><expr><name>__GNUG__</name></expr></argument>)</argument_list></call><operator>)</operator></expr></cpp:if>
<cpp:if>#<cpp:directive>if</cpp:directive> <expr><operator>!</operator><call><name>defined</name><argument_list>(<argument><expr><name>_WCHAR_T</name></expr></argument>)</argument_list></call></expr></cpp:if>
<cpp:define>#<cpp:directive>define</cpp:directive> <cpp:macro><name>_WCHAR_T</name></cpp:macro></cpp:define>
<cpp:if>#<cpp:directive>if</cpp:directive> <expr><call><name>defined</name><argument_list>(<argument><expr><name>_LP64</name></expr></argument>)</argument_list></call></expr></cpp:if>
<typedef>typedef <type><name>int</name></type> <name>wchar_t</name>;</typedef>
<cpp:else>#<cpp:directive>else</cpp:directive></cpp:else>
<typedef>typedef <type><name>long</name></type> <name>wchar_t</name>;</typedef>
<cpp:endif>#<cpp:directive>endif</cpp:directive></cpp:endif>
<cpp:endif>#<cpp:directive>endif</cpp:directive></cpp:endif>
<cpp:endif>#<cpp:directive>endif</cpp:directive></cpp:endif>

<cpp:define>#<cpp:directive>define</cpp:directive> <cpp:macro><name>TEXTDOMAINMAX</name></cpp:macro> <cpp:value>256</cpp:value></cpp:define>

<cpp:define>#<cpp:directive>define</cpp:directive> <cpp:macro><name>__GNU_GETTEXT_SUPPORTED_REVISION</name><parameter_list>(<parameter><type><name>m</name></type></parameter>)</parameter_list></cpp:macro> <cpp:value>((((m) == 0) || ((m) == 1)) ? 1 : -1)</cpp:value></cpp:define>


<function_decl><type><specifier>extern</specifier> <name>char</name> <modifier>*</modifier></type><name>dcgettext</name><parameter_list>(<parameter><decl><type><specifier>const</specifier> <name>char</name> <modifier>*</modifier></type></decl></parameter>, <parameter><decl><type><specifier>const</specifier> <name>char</name> <modifier>*</modifier></type></decl></parameter>, <parameter><decl><type><specifier>const</specifier> <name>int</name></type></decl></parameter>)</parameter_list>;</function_decl>
<function_decl><type><specifier>extern</specifier> <name>char</name> <modifier>*</modifier></type><name>dgettext</name><parameter_list>(<parameter><decl><type><specifier>const</specifier> <name>char</name> <modifier>*</modifier></type></decl></parameter>, <parameter><decl><type><specifier>const</specifier> <name>char</name> <modifier>*</modifier></type></decl></parameter>)</parameter_list>;</function_decl>
<function_decl><type><specifier>extern</specifier> <name>char</name> <modifier>*</modifier></type><name>gettext</name><parameter_list>(<parameter><decl><type><specifier>const</specifier> <name>char</name> <modifier>*</modifier></type></decl></parameter>)</parameter_list>;</function_decl>
<function_decl><type><specifier>extern</specifier> <name>char</name> <modifier>*</modifier></type><name>textdomain</name><parameter_list>(<parameter><decl><type><specifier>const</specifier> <name>char</name> <modifier>*</modifier></type></decl></parameter>)</parameter_list>;</function_decl>
<function_decl><type><specifier>extern</specifier> <name>char</name> <modifier>*</modifier></type><name>bindtextdomain</name><parameter_list>(<parameter><decl><type><specifier>const</specifier> <name>char</name> <modifier>*</modifier></type></decl></parameter>, <parameter><decl><type><specifier>const</specifier> <name>char</name> <modifier>*</modifier></type></decl></parameter>)</parameter_list>;</function_decl>





<function_decl><type><specifier>extern</specifier> <name>char</name> <modifier>*</modifier></type><name>dcngettext</name><parameter_list>(<parameter><decl><type><specifier>const</specifier> <name>char</name> <modifier>*</modifier></type></decl></parameter>, <parameter><decl><type><specifier>const</specifier> <name>char</name> <modifier>*</modifier></type></decl></parameter>,
<parameter><decl><type><specifier>const</specifier> <name>char</name> <modifier>*</modifier></type></decl></parameter>, <parameter><decl><type><name>unsigned</name> <name>long</name></type> <name>int</name></decl></parameter>, <parameter><decl><type><name>int</name></type></decl></parameter>)</parameter_list>;</function_decl>
<function_decl><type><specifier>extern</specifier> <name>char</name> <modifier>*</modifier></type><name>dngettext</name><parameter_list>(<parameter><decl><type><specifier>const</specifier> <name>char</name> <modifier>*</modifier></type></decl></parameter>, <parameter><decl><type><specifier>const</specifier> <name>char</name> <modifier>*</modifier></type></decl></parameter>,
<parameter><decl><type><specifier>const</specifier> <name>char</name> <modifier>*</modifier></type></decl></parameter>, <parameter><decl><type><name>unsigned</name> <name>long</name></type> <name>int</name></decl></parameter>)</parameter_list>;</function_decl>
<function_decl><type><specifier>extern</specifier> <name>char</name> <modifier>*</modifier></type><name>ngettext</name><parameter_list>(<parameter><decl><type><specifier>const</specifier> <name>char</name> <modifier>*</modifier></type></decl></parameter>, <parameter><decl><type><specifier>const</specifier> <name>char</name> <modifier>*</modifier></type></decl></parameter>, <parameter><decl><type><name>unsigned</name> <name>long</name></type> <name>int</name></decl></parameter>)</parameter_list>;</function_decl>
<function_decl><type><specifier>extern</specifier> <name>char</name> <modifier>*</modifier></type><name>bind_textdomain_codeset</name><parameter_list>(<parameter><decl><type><specifier>const</specifier> <name>char</name> <modifier>*</modifier></type></decl></parameter>, <parameter><decl><type><specifier>const</specifier> <name>char</name> <modifier>*</modifier></type></decl></parameter>)</parameter_list>;</function_decl>



<function_decl><type><specifier>extern</specifier> <name>int</name></type> <name>wdinit</name><parameter_list>(<parameter><decl><type><name>void</name></type></decl></parameter>)</parameter_list>;</function_decl>
<function_decl><type><specifier>extern</specifier> <name>int</name></type> <name>wdchkind</name><parameter_list>(<parameter><decl><type><name>wchar_t</name></type></decl></parameter>)</parameter_list>;</function_decl>
<function_decl><type><specifier>extern</specifier> <name>int</name></type> <name>wdbindf</name><parameter_list>(<parameter><decl><type><name>wchar_t</name></type></decl></parameter>, <parameter><decl><type><name>wchar_t</name></type></decl></parameter>, <parameter><decl><type><name>int</name></type></decl></parameter>)</parameter_list>;</function_decl>
<function_decl><type><specifier>extern</specifier> <name>wchar_t</name> <modifier>*</modifier></type><name>wddelim</name><parameter_list>(<parameter><decl><type><name>wchar_t</name></type></decl></parameter>, <parameter><decl><type><name>wchar_t</name></type></decl></parameter>, <parameter><decl><type><name>int</name></type></decl></parameter>)</parameter_list>;</function_decl>
<function_decl><type><specifier>extern</specifier> <name>wchar_t</name></type> <name>mcfiller</name><parameter_list>(<parameter><decl><type><name>void</name></type></decl></parameter>)</parameter_list>;</function_decl>
<function_decl><type><specifier>extern</specifier> <name>int</name></type> <name>mcwrap</name><parameter_list>(<parameter><decl><type><name>void</name></type></decl></parameter>)</parameter_list>;</function_decl>

<cpp:if>#<cpp:directive>if</cpp:directive> <expr><call><name>defined</name><argument_list>(<argument><expr><name>__cplusplus</name></expr></argument>)</argument_list></call></expr></cpp:if>
</block_content>}</block></extern>
<cpp:endif>#<cpp:directive>endif</cpp:directive></cpp:endif>

<cpp:endif>#<cpp:directive>endif</cpp:directive></cpp:endif>
</unit>
