<?xml version="1.0" encoding="UTF-8" standalone="yes"?>
<unit xmlns="http://www.srcML.org/srcML/src" xmlns:cpp="http://www.srcML.org/srcML/cpp" revision="1.0.0" language="C" filename="/home/user/cppstats/test/freeBSD_res/_cppstats_featurelocations/freebsd-src/contrib/libarchive/libarchive_fe/passphrase.h">
























<cpp:if>#<cpp:directive>if</cpp:directive> <expr><operator>!</operator><call><name>defined</name><argument_list>(<argument><expr><name>LAFE_PASSPHRASE_H</name></expr></argument>)</argument_list></call></expr></cpp:if>
<cpp:define>#<cpp:directive>define</cpp:directive> <cpp:macro><name>LAFE_PASSPHRASE_H</name></cpp:macro></cpp:define>

<function_decl><type><name>char</name> <modifier>*</modifier></type><name>lafe_readpassphrase</name><parameter_list>(<parameter><decl><type><specifier>const</specifier> <name>char</name> <modifier>*</modifier></type><name>prompt</name></decl></parameter>, <parameter><decl><type><name>char</name> <modifier>*</modifier></type><name>buf</name></decl></parameter>, <parameter><decl><type><name>size_t</name></type> <name>bufsiz</name></decl></parameter>)</parameter_list>;</function_decl>

<cpp:endif>#<cpp:directive>endif</cpp:directive></cpp:endif>
</unit>
