<?xml version="1.0" encoding="UTF-8" standalone="yes"?>
<unit xmlns="http://www.srcML.org/srcML/src" xmlns:cpp="http://www.srcML.org/srcML/cpp" revision="1.0.0" language="C" filename="/home/user/cppstats/test/freeBSD_res/_cppstats_featurelocations/freebsd-src/contrib/llvm-project/clang/include/clang/Driver/Phases.h">







<cpp:if>#<cpp:directive>if</cpp:directive> <expr><operator>!</operator><call><name>defined</name><argument_list>(<argument><expr><name>LLVM_CLANG_DRIVER_PHASES_H</name></expr></argument>)</argument_list></call></expr></cpp:if>
<cpp:define>#<cpp:directive>define</cpp:directive> <cpp:macro><name>LLVM_CLANG_DRIVER_PHASES_H</name></cpp:macro></cpp:define>

<decl_stmt><decl><type><name>namespace</name></type> <name>clang</name> <block>{<block_content>
<decl_stmt><decl><type><name>namespace</name></type> <name>driver</name> <block>{<block_content>
<decl_stmt><decl><type><name>namespace</name></type> <name>phases</name> <block>{<block_content>


<enum>enum <name>ID</name> <block>{
<decl><name>Preprocess</name></decl>,
<decl><name>Precompile</name></decl>,
<decl><name>Compile</name></decl>,
<decl><name>Backend</name></decl>,
<decl><name>Assemble</name></decl>,
<decl><name>Link</name></decl>,
<decl><name>IfsMerge</name></decl>,
<decl><name>LastPhase</name> <init>= <expr><name>IfsMerge</name></expr></init></decl>,
}</block>;</enum>

<enum>enum <block>{
<decl><name>MaxNumberOfPhases</name> <init>= <expr><name>LastPhase</name> <operator>+</operator> <literal type="number">1</literal></expr></init></decl>
}</block>;</enum>

<function_decl><type><specifier>const</specifier> <name>char</name> <modifier>*</modifier></type><name>getPhaseName</name><parameter_list>(<parameter><decl><type><name>ID</name></type> <name>Id</name></decl></parameter>)</parameter_list>;</function_decl>

</block_content>}</block></decl></decl_stmt>
</block_content>}</block></decl></decl_stmt>
</block_content>}</block></decl></decl_stmt>

<cpp:endif>#<cpp:directive>endif</cpp:directive></cpp:endif>
</unit>
